README.md
setup.py
esvg/__init__.py
esvg/easings.py
esvg/esvg.py
esvg/exceptions.py
esvg.egg-info/PKG-INFO
esvg.egg-info/SOURCES.txt
esvg.egg-info/dependency_links.txt
esvg.egg-info/not-zip-safe
esvg.egg-info/top_level.txt