Metadata-Version: 1.0
Name: esvg
Version: 0.0.3
Summary: A library to generate animated SVGs
Home-page: http://github.com/lletfrix/esvg
Author: Rafael Sánchez
Author-email: lletfrix@gmail.com
License: MIT
Platform: UNKNOWN
